{"Data":{"TotalCount":3459,"Data":[{"Ngay":"03/01/2024","GiaDieuChinh":11,"GiaDongCua":11,"ThayDoi":"0(0.00 %)","KhoiLuongKhopLenh":37121,"GiaTriKhopLenh":403928900,"KLThoaThuan":0,"GtThoaThuan":0,"GiaMoCua":11,"GiaCaoNhat":11,"GiaThapNhat":10.8},{"Ngay":"02/01/2024","GiaDieuChinh":11,"GiaDongCua":11,"ThayDoi":"0(0.00 %)","KhoiLuongKhopLenh":37247,"GiaTriKhopLenh":408514000,"KLThoaThuan":0,"GtThoaThuan":0,"GiaMoCua":11,"GiaCaoNhat":11,"GiaThapNhat":10.9},{"Ngay":"29/12/2023","GiaDieuChinh":11,"GiaDongCua":11,"ThayDoi":"0(0.00 %)","KhoiLuongKhopLenh":36300,"GiaTriKhopLenh":394680000,"KLThoaThuan":0,"GtThoaThuan":0,"GiaMoCua":11.5,"GiaCaoNhat":11.5,"GiaThapNhat":10.8},{"Ngay":"28/12/2023","GiaDieuChinh":11,"GiaDongCua":11,"ThayDoi":"0.4(3.77 %)","KhoiLuongKhopLenh":8100,"GiaTriKhopLenh":88730000,"KLThoaThuan":0,"GtThoaThuan":0,"GiaMoCua":11.4,"GiaCaoNhat":11.4,"GiaThapNhat":10.9},{"Ngay":"27/12/2023","GiaDieuChinh":10.6,"GiaDongCua":10.6,"ThayDoi":"-0.4(-3.64 %)","KhoiLuongKhopLenh":23200,"GiaTriKhopLenh":250540000,"KLThoaThuan":0,"GtThoaThuan":0,"GiaMoCua":11.4,"GiaCaoNhat":11.4,"GiaThapNhat":10.6},{"Ngay":"26/12/2023","GiaDieuChinh":11,"GiaDongCua":11,"ThayDoi":"0(0.00 %)","KhoiLuongKhopLenh":26300,"GiaTriKhopLenh":285750000,"KLThoaThuan":0,"GtThoaThuan":0,"GiaMoCua":10.9,"GiaCaoNhat":11.1,"GiaThapNhat":10},{"Ngay":"25/12/2023","GiaDieuChinh":11,"GiaDongCua":11,"ThayDoi":"0(0.00 %)","KhoiLuongKhopLenh":11705,"GiaTriKhopLenh":128755000,"KLThoaThuan":0,"GtThoaThuan":0,"GiaMoCua":11,"GiaCaoNhat":11,"GiaThapNhat":11},{"Ngay":"22/12/2023","GiaDieuChinh":11,"GiaDongCua":11,"ThayDoi":"0(0.00 %)","KhoiLuongKhopLenh":15300,"GiaTriKhopLenh":168300000,"KLThoaThuan":0,"GtThoaThuan":0,"GiaMoCua":11,"GiaCaoNhat":11,"GiaThapNhat":11},{"Ngay":"21/12/2023","GiaDieuChinh":11,"GiaDongCua":11,"ThayDoi":"0(0.00 %)","KhoiLuongKhopLenh":0,"GiaTriKhopLenh":0,"KLThoaThuan":0,"GtThoaThuan":0,"GiaMoCua":11,"GiaCaoNhat":11,"GiaThapNhat":11},{"Ngay":"20/12/2023","GiaDieuChinh":11,"GiaDongCua":11,"ThayDoi":"0(0.00 %)","KhoiLuongKhopLenh":5500,"GiaTriKhopLenh":60500000,"KLThoaThuan":0,"GtThoaThuan":0,"GiaMoCua":11,"GiaCaoNhat":11,"GiaThapNhat":11},{"Ngay":"19/12/2023","GiaDieuChinh":11,"GiaDongCua":11,"ThayDoi":"-0.2(-1.79 %)","KhoiLuongKhopLenh":7300,"GiaTriKhopLenh":80340000,"KLThoaThuan":0,"GtThoaThuan":0,"GiaMoCua":11.4,"GiaCaoNhat":11.4,"GiaThapNhat":11},{"Ngay":"18/12/2023","GiaDieuChinh":11.2,"GiaDongCua":11.2,"ThayDoi":"0.2(1.82 %)","KhoiLuongKhopLenh":18100,"GiaTriKhopLenh":201790000,"KLThoaThuan":0,"GtThoaThuan":0,"GiaMoCua":11.2,"GiaCaoNhat":11.3,"GiaThapNhat":11},{"Ngay":"15/12/2023","GiaDieuChinh":11,"GiaDongCua":11,"ThayDoi":"-0.2(-1.79 %)","KhoiLuongKhopLenh":21065,"GiaTriKhopLenh":231715000,"KLThoaThuan":0,"GtThoaThuan":0,"GiaMoCua":11,"GiaCaoNhat":11,"GiaThapNhat":11},{"Ngay":"14/12/2023","GiaDieuChinh":11.2,"GiaDongCua":11.2,"ThayDoi":"-0.1(-0.88 %)","KhoiLuongKhopLenh":707,"GiaTriKhopLenh":7769800,"KLThoaThuan":0,"GtThoaThuan":0,"GiaMoCua":11.1,"GiaCaoNhat":11.2,"GiaThapNhat":10.7},{"Ngay":"13/12/2023","GiaDieuChinh":11.3,"GiaDongCua":11.3,"ThayDoi":"0(0.00 %)","KhoiLuongKhopLenh":48562,"GiaTriKhopLenh":548664100,"KLThoaThuan":0,"GtThoaThuan":0,"GiaMoCua":11.4,"GiaCaoNhat":11.4,"GiaThapNhat":11.1},{"Ngay":"12/12/2023","GiaDieuChinh":11.3,"GiaDongCua":11.3,"ThayDoi":"0.3(2.73 %)","KhoiLuongKhopLenh":13400,"GiaTriKhopLenh":147430000,"KLThoaThuan":0,"GtThoaThuan":0,"GiaMoCua":11,"GiaCaoNhat":11.3,"GiaThapNhat":11},{"Ngay":"11/12/2023","GiaDieuChinh":11,"GiaDongCua":11,"ThayDoi":"-0.3(-2.65 %)","KhoiLuongKhopLenh":300,"GiaTriKhopLenh":3370000,"KLThoaThuan":0,"GtThoaThuan":0,"GiaMoCua":11.7,"GiaCaoNhat":11.7,"GiaThapNhat":11},{"Ngay":"08/12/2023","GiaDieuChinh":11.3,"GiaDongCua":11.3,"ThayDoi":"0(0.00 %)","KhoiLuongKhopLenh":21615,"GiaTriKhopLenh":244579500,"KLThoaThuan":471000,"GtThoaThuan":5211615000,"GiaMoCua":12.4,"GiaCaoNhat":12.4,"GiaThapNhat":11.3},{"Ngay":"07/12/2023","GiaDieuChinh":11.3,"GiaDongCua":11.3,"ThayDoi":"0.2(1.80 %)","KhoiLuongKhopLenh":32000,"GiaTriKhopLenh":357200000,"KLThoaThuan":0,"GtThoaThuan":0,"GiaMoCua":11.4,"GiaCaoNhat":11.4,"GiaThapNhat":11},{"Ngay":"06/12/2023","GiaDieuChinh":11.1,"GiaDongCua":11.6,"ThayDoi":"0(0.00 %)","KhoiLuongKhopLenh":79500,"GiaTriKhopLenh":916300000,"KLThoaThuan":471000,"GtThoaThuan":5463600000,"GiaMoCua":11.5,"GiaCaoNhat":11.6,"GiaThapNhat":11.4},{"Ngay":"05/12/2023","GiaDieuChinh":11.1,"GiaDongCua":11.6,"ThayDoi":"0(0.00 %)","KhoiLuongKhopLenh":3900,"GiaTriKhopLenh":45180000,"KLThoaThuan":0,"GtThoaThuan":0,"GiaMoCua":11.5,"GiaCaoNhat":11.6,"GiaThapNhat":11.4},{"Ngay":"04/12/2023","GiaDieuChinh":11.1,"GiaDongCua":11.6,"ThayDoi":"0.1(0.87 %)","KhoiLuongKhopLenh":5760,"GiaTriKhopLenh":66495600,"KLThoaThuan":0,"GtThoaThuan":0,"GiaMoCua":11.5,"GiaCaoNhat":11.6,"GiaThapNhat":11.4},{"Ngay":"01/12/2023","GiaDieuChinh":11.5,"GiaDongCua":11.5,"ThayDoi":"0.3(2.68 %)","KhoiLuongKhopLenh":4500,"GiaTriKhopLenh":51580000,"KLThoaThuan":0,"GtThoaThuan":0,"GiaMoCua":11.2,"GiaCaoNhat":11.5,"GiaThapNhat":11.2},{"Ngay":"30/11/2023","GiaDieuChinh":10.71,"GiaDongCua":11.2,"ThayDoi":"0(0.00 %)","KhoiLuongKhopLenh":7900,"GiaTriKhopLenh":88630000,"KLThoaThuan":0,"GtThoaThuan":0,"GiaMoCua":11.3,"GiaCaoNhat":11.4,"GiaThapNhat":11.2},{"Ngay":"29/11/2023","GiaDieuChinh":10.71,"GiaDongCua":11.2,"ThayDoi":"-0.5(-4.27 %)","KhoiLuongKhopLenh":18200,"GiaTriKhopLenh":206770000,"KLThoaThuan":0,"GtThoaThuan":0,"GiaMoCua":11.9,"GiaCaoNhat":11.9,"GiaThapNhat":11.2},{"Ngay":"28/11/2023","GiaDieuChinh":11.19,"GiaDongCua":11.7,"ThayDoi":"0(0.00 %)","KhoiLuongKhopLenh":2900,"GiaTriKhopLenh":34030000,"KLThoaThuan":0,"GtThoaThuan":0,"GiaMoCua":11.9,"GiaCaoNhat":11.9,"GiaThapNhat":11.7},{"Ngay":"27/11/2023","GiaDieuChinh":11.19,"GiaDongCua":11.7,"ThayDoi":"0.4(3.54 %)","KhoiLuongKhopLenh":24650,"GiaTriKhopLenh":288085000,"KLThoaThuan":0,"GtThoaThuan":0,"GiaMoCua":11.4,"GiaCaoNhat":12,"GiaThapNhat":11.4},{"Ngay":"24/11/2023","GiaDieuChinh":10.81,"GiaDongCua":11.3,"ThayDoi":"0(0.00 %)","KhoiLuongKhopLenh":11301,"GiaTriKhopLenh":128961500,"KLThoaThuan":0,"GtThoaThuan":0,"GiaMoCua":11.3,"GiaCaoNhat":11.6,"GiaThapNhat":11.3},{"Ngay":"23/11/2023","GiaDieuChinh":10.81,"GiaDongCua":11.3,"ThayDoi":"0(0.00 %)","KhoiLuongKhopLenh":0,"GiaTriKhopLenh":0,"KLThoaThuan":0,"GtThoaThuan":0,"GiaMoCua":11.3,"GiaCaoNhat":11.3,"GiaThapNhat":11.3},{"Ngay":"22/11/2023","GiaDieuChinh":10.81,"GiaDongCua":11.3,"ThayDoi":"0.1(0.89 %)","KhoiLuongKhopLenh":6712,"GiaTriKhopLenh":74665000,"KLThoaThuan":470000,"GtThoaThuan":4794000000,"GiaMoCua":11.2,"GiaCaoNhat":11.3,"GiaThapNhat":11.1},{"Ngay":"21/11/2023","GiaDieuChinh":10.71,"GiaDongCua":11.2,"ThayDoi":"0.2(1.82 %)","KhoiLuongKhopLenh":100,"GiaTriKhopLenh":1120000,"KLThoaThuan":0,"GtThoaThuan":0,"GiaMoCua":11.2,"GiaCaoNhat":11.2,"GiaThapNhat":11.2},{"Ngay":"20/11/2023","GiaDieuChinh":10.52,"GiaDongCua":11,"ThayDoi":"-0.1(-0.90 %)","KhoiLuongKhopLenh":826,"GiaTriKhopLenh":9097600,"KLThoaThuan":0,"GtThoaThuan":0,"GiaMoCua":11.1,"GiaCaoNhat":11.1,"GiaThapNhat":11},{"Ngay":"17/11/2023","GiaDieuChinh":10.62,"GiaDongCua":11.1,"ThayDoi":"0(0.00 %)","KhoiLuongKhopLenh":300,"GiaTriKhopLenh":3320000,"KLThoaThuan":0,"GtThoaThuan":0,"GiaMoCua":11.1,"GiaCaoNhat":11.1,"GiaThapNhat":11},{"Ngay":"16/11/2023","GiaDieuChinh":10.62,"GiaDongCua":11.1,"ThayDoi":"0.1(0.91 %)","KhoiLuongKhopLenh":4001,"GiaTriKhopLenh":44331500,"KLThoaThuan":0,"GtThoaThuan":0,"GiaMoCua":11,"GiaCaoNhat":11.2,"GiaThapNhat":11},{"Ngay":"15/11/2023","GiaDieuChinh":10.52,"GiaDongCua":11,"ThayDoi":"0(0.00 %)","KhoiLuongKhopLenh":5900,"GiaTriKhopLenh":65040000,"KLThoaThuan":0,"GtThoaThuan":0,"GiaMoCua":11.1,"GiaCaoNhat":11.1,"GiaThapNhat":11},{"Ngay":"14/11/2023","GiaDieuChinh":10.52,"GiaDongCua":11,"ThayDoi":"-0.2(-1.79 %)","KhoiLuongKhopLenh":8916,"GiaTriKhopLenh":98451500,"KLThoaThuan":0,"GtThoaThuan":0,"GiaMoCua":11.5,"GiaCaoNhat":11.5,"GiaThapNhat":10.9},{"Ngay":"13/11/2023","GiaDieuChinh":10.71,"GiaDongCua":11.2,"ThayDoi":"0.3(2.75 %)","KhoiLuongKhopLenh":8608,"GiaTriKhopLenh":97642000,"KLThoaThuan":0,"GtThoaThuan":0,"GiaMoCua":10.9,"GiaCaoNhat":11.6,"GiaThapNhat":10.9},{"Ngay":"10/11/2023","GiaDieuChinh":10.43,"GiaDongCua":10.9,"ThayDoi":"-0.3(-2.68 %)","KhoiLuongKhopLenh":73815,"GiaTriKhopLenh":793355300,"KLThoaThuan":0,"GtThoaThuan":0,"GiaMoCua":11,"GiaCaoNhat":11.1,"GiaThapNhat":10.2},{"Ngay":"09/11/2023","GiaDieuChinh":10.71,"GiaDongCua":11.2,"ThayDoi":"0.1(0.90 %)","KhoiLuongKhopLenh":6715,"GiaTriKhopLenh":74069500,"KLThoaThuan":0,"GtThoaThuan":0,"GiaMoCua":11.3,"GiaCaoNhat":11.4,"GiaThapNhat":11},{"Ngay":"08/11/2023","GiaDieuChinh":10.62,"GiaDongCua":11.1,"ThayDoi":"0.1(0.91 %)","KhoiLuongKhopLenh":1001,"GiaTriKhopLenh":11441000,"KLThoaThuan":0,"GtThoaThuan":0,"GiaMoCua":12.1,"GiaCaoNhat":12.1,"GiaThapNhat":11.1},{"Ngay":"07/11/2023","GiaDieuChinh":10.52,"GiaDongCua":11,"ThayDoi":"0(0.00 %)","KhoiLuongKhopLenh":100,"GiaTriKhopLenh":1100000,"KLThoaThuan":0,"GtThoaThuan":0,"GiaMoCua":11,"GiaCaoNhat":11,"GiaThapNhat":11},{"Ngay":"06/11/2023","GiaDieuChinh":10.52,"GiaDongCua":11,"ThayDoi":"0.1(0.92 %)","KhoiLuongKhopLenh":100,"GiaTriKhopLenh":1100000,"KLThoaThuan":0,"GtThoaThuan":0,"GiaMoCua":11,"GiaCaoNhat":11,"GiaThapNhat":11},{"Ngay":"03/11/2023","GiaDieuChinh":10.43,"GiaDongCua":10.9,"ThayDoi":"0(0.00 %)","KhoiLuongKhopLenh":102,"GiaTriKhopLenh":1111800,"KLThoaThuan":0,"GtThoaThuan":0,"GiaMoCua":10.9,"GiaCaoNhat":10.9,"GiaThapNhat":10.9},{"Ngay":"02/11/2023","GiaDieuChinh":10.43,"GiaDongCua":10.9,"ThayDoi":"0.1(0.93 %)","KhoiLuongKhopLenh":2000,"GiaTriKhopLenh":21570000,"KLThoaThuan":0,"GtThoaThuan":0,"GiaMoCua":10.8,"GiaCaoNhat":10.9,"GiaThapNhat":10.7},{"Ngay":"01/11/2023","GiaDieuChinh":10.33,"GiaDongCua":10.8,"ThayDoi":"-0.3(-2.70 %)","KhoiLuongKhopLenh":9702,"GiaTriKhopLenh":105181600,"KLThoaThuan":0,"GtThoaThuan":0,"GiaMoCua":11,"GiaCaoNhat":11,"GiaThapNhat":10.8},{"Ngay":"31/10/2023","GiaDieuChinh":10.62,"GiaDongCua":11.1,"ThayDoi":"0(0.00 %)","KhoiLuongKhopLenh":1000,"GiaTriKhopLenh":11080000,"KLThoaThuan":0,"GtThoaThuan":0,"GiaMoCua":11.1,"GiaCaoNhat":11.1,"GiaThapNhat":11},{"Ngay":"30/10/2023","GiaDieuChinh":10.62,"GiaDongCua":11.1,"ThayDoi":"0(0.00 %)","KhoiLuongKhopLenh":7800,"GiaTriKhopLenh":84860000,"KLThoaThuan":0,"GtThoaThuan":0,"GiaMoCua":11.1,"GiaCaoNhat":11.1,"GiaThapNhat":10.5},{"Ngay":"26/10/2023","GiaDieuChinh":10.71,"GiaDongCua":11.2,"ThayDoi":"0(0.00 %)","KhoiLuongKhopLenh":1000,"GiaTriKhopLenh":11120000,"KLThoaThuan":0,"GtThoaThuan":0,"GiaMoCua":11.2,"GiaCaoNhat":11.2,"GiaThapNhat":11.1},{"Ngay":"25/10/2023","GiaDieuChinh":10.71,"GiaDongCua":11.2,"ThayDoi":"-0.1(-0.88 %)","KhoiLuongKhopLenh":3251,"GiaTriKhopLenh":36531300,"KLThoaThuan":0,"GtThoaThuan":0,"GiaMoCua":11.3,"GiaCaoNhat":11.3,"GiaThapNhat":11.2},{"Ngay":"24/10/2023","GiaDieuChinh":10.81,"GiaDongCua":11.3,"ThayDoi":"0(0.00 %)","KhoiLuongKhopLenh":3200,"GiaTriKhopLenh":35940000,"KLThoaThuan":0,"GtThoaThuan":0,"GiaMoCua":11.3,"GiaCaoNhat":11.3,"GiaThapNhat":11.2},{"Ngay":"23/10/2023","GiaDieuChinh":10.81,"GiaDongCua":11.3,"ThayDoi":"0(0.00 %)","KhoiLuongKhopLenh":3200,"GiaTriKhopLenh":35960000,"KLThoaThuan":0,"GtThoaThuan":0,"GiaMoCua":11.3,"GiaCaoNhat":11.3,"GiaThapNhat":11.2},{"Ngay":"20/10/2023","GiaDieuChinh":10.81,"GiaDongCua":11.3,"ThayDoi":"0.1(0.89 %)","KhoiLuongKhopLenh":3365,"GiaTriKhopLenh":37873300,"KLThoaThuan":0,"GtThoaThuan":0,"GiaMoCua":11.2,"GiaCaoNhat":11.4,"GiaThapNhat":11.2},{"Ngay":"19/10/2023","GiaDieuChinh":10.71,"GiaDongCua":11.2,"ThayDoi":"0(0.00 %)","KhoiLuongKhopLenh":11000,"GiaTriKhopLenh":123570000,"KLThoaThuan":0,"GtThoaThuan":0,"GiaMoCua":11.3,"GiaCaoNhat":11.5,"GiaThapNhat":11.2},{"Ngay":"18/10/2023","GiaDieuChinh":10.71,"GiaDongCua":11.2,"ThayDoi":"-0.3(-2.61 %)","KhoiLuongKhopLenh":20413,"GiaTriKhopLenh":230698200,"KLThoaThuan":0,"GtThoaThuan":0,"GiaMoCua":11.4,"GiaCaoNhat":11.4,"GiaThapNhat":11.2},{"Ngay":"17/10/2023","GiaDieuChinh":11,"GiaDongCua":11.5,"ThayDoi":"0(0.00 %)","KhoiLuongKhopLenh":31220,"GiaTriKhopLenh":357962000,"KLThoaThuan":0,"GtThoaThuan":0,"GiaMoCua":11.5,"GiaCaoNhat":11.7,"GiaThapNhat":11.4},{"Ngay":"16/10/2023","GiaDieuChinh":11,"GiaDongCua":11.5,"ThayDoi":"0(0.00 %)","KhoiLuongKhopLenh":23492,"GiaTriKhopLenh":269790500,"KLThoaThuan":0,"GtThoaThuan":0,"GiaMoCua":12,"GiaCaoNhat":12,"GiaThapNhat":11.4},{"Ngay":"13/10/2023","GiaDieuChinh":11,"GiaDongCua":11.5,"ThayDoi":"-0.5(-4.17 %)","KhoiLuongKhopLenh":11700,"GiaTriKhopLenh":134640000,"KLThoaThuan":0,"GtThoaThuan":0,"GiaMoCua":11.8,"GiaCaoNhat":11.8,"GiaThapNhat":11.5},{"Ngay":"12/10/2023","GiaDieuChinh":11.48,"GiaDongCua":12,"ThayDoi":"0.1(0.84 %)","KhoiLuongKhopLenh":10300,"GiaTriKhopLenh":123590000,"KLThoaThuan":0,"GtThoaThuan":0,"GiaMoCua":11.9,"GiaCaoNhat":12,"GiaThapNhat":11.9},{"Ngay":"11/10/2023","GiaDieuChinh":11.38,"GiaDongCua":11.9,"ThayDoi":"-0.1(-0.83 %)","KhoiLuongKhopLenh":30100,"GiaTriKhopLenh":352620000,"KLThoaThuan":0,"GtThoaThuan":0,"GiaMoCua":12,"GiaCaoNhat":12,"GiaThapNhat":11.6},{"Ngay":"10/10/2023","GiaDieuChinh":11.48,"GiaDongCua":12,"ThayDoi":"0(0.00 %)","KhoiLuongKhopLenh":1100,"GiaTriKhopLenh":13170000,"KLThoaThuan":0,"GtThoaThuan":0,"GiaMoCua":11.9,"GiaCaoNhat":12,"GiaThapNhat":11.9},{"Ngay":"09/10/2023","GiaDieuChinh":11.48,"GiaDongCua":12,"ThayDoi":"0.2(1.69 %)","KhoiLuongKhopLenh":950,"GiaTriKhopLenh":11090200,"KLThoaThuan":0,"GtThoaThuan":0,"GiaMoCua":11.5,"GiaCaoNhat":12,"GiaThapNhat":11.5},{"Ngay":"06/10/2023","GiaDieuChinh":11.29,"GiaDongCua":11.8,"ThayDoi":"0(0.00 %)","KhoiLuongKhopLenh":0,"GiaTriKhopLenh":0,"KLThoaThuan":0,"GtThoaThuan":0,"GiaMoCua":11.8,"GiaCaoNhat":11.8,"GiaThapNhat":11.8},{"Ngay":"05/10/2023","GiaDieuChinh":11.29,"GiaDongCua":11.8,"ThayDoi":"-0.2(-1.67 %)","KhoiLuongKhopLenh":100,"GiaTriKhopLenh":1180000,"KLThoaThuan":0,"GtThoaThuan":0,"GiaMoCua":11.8,"GiaCaoNhat":11.8,"GiaThapNhat":11.8},{"Ngay":"04/10/2023","GiaDieuChinh":11.48,"GiaDongCua":12,"ThayDoi":"0.5(4.35 %)","KhoiLuongKhopLenh":2550,"GiaTriKhopLenh":29777500,"KLThoaThuan":0,"GtThoaThuan":0,"GiaMoCua":11.5,"GiaCaoNhat":12,"GiaThapNhat":11.5},{"Ngay":"03/10/2023","GiaDieuChinh":11,"GiaDongCua":11.5,"ThayDoi":"-0.3(-2.54 %)","KhoiLuongKhopLenh":800,"GiaTriKhopLenh":9240000,"KLThoaThuan":0,"GtThoaThuan":0,"GiaMoCua":11.6,"GiaCaoNhat":11.6,"GiaThapNhat":11.5},{"Ngay":"02/10/2023","GiaDieuChinh":11.29,"GiaDongCua":11.8,"ThayDoi":"0.1(0.85 %)","KhoiLuongKhopLenh":2400,"GiaTriKhopLenh":27860000,"KLThoaThuan":0,"GtThoaThuan":0,"GiaMoCua":11.6,"GiaCaoNhat":11.8,"GiaThapNhat":11.6},{"Ngay":"29/09/2023","GiaDieuChinh":11.19,"GiaDongCua":11.7,"ThayDoi":"0.2(1.74 %)","KhoiLuongKhopLenh":1918,"GiaTriKhopLenh":22675000,"KLThoaThuan":0,"GtThoaThuan":0,"GiaMoCua":11.4,"GiaCaoNhat":12,"GiaThapNhat":11.4},{"Ngay":"28/09/2023","GiaDieuChinh":11,"GiaDongCua":11.5,"ThayDoi":"-0.5(-4.17 %)","KhoiLuongKhopLenh":1500,"GiaTriKhopLenh":17590000,"KLThoaThuan":0,"GtThoaThuan":0,"GiaMoCua":12,"GiaCaoNhat":12,"GiaThapNhat":11.5},{"Ngay":"27/09/2023","GiaDieuChinh":11.48,"GiaDongCua":12,"ThayDoi":"0(0.00 %)","KhoiLuongKhopLenh":2100,"GiaTriKhopLenh":25200000,"KLThoaThuan":0,"GtThoaThuan":0,"GiaMoCua":12,"GiaCaoNhat":12,"GiaThapNhat":12},{"Ngay":"26/09/2023","GiaDieuChinh":11.48,"GiaDongCua":12,"ThayDoi":"0.1(0.84 %)","KhoiLuongKhopLenh":1300,"GiaTriKhopLenh":15900000,"KLThoaThuan":0,"GtThoaThuan":0,"GiaMoCua":12.3,"GiaCaoNhat":12.3,"GiaThapNhat":12},{"Ngay":"25/09/2023","GiaDieuChinh":11.38,"GiaDongCua":11.9,"ThayDoi":"-0.6(-4.80 %)","KhoiLuongKhopLenh":3900,"GiaTriKhopLenh":47240000,"KLThoaThuan":0,"GtThoaThuan":0,"GiaMoCua":12.3,"GiaCaoNhat":12.3,"GiaThapNhat":11.9},{"Ngay":"22/09/2023","GiaDieuChinh":11.96,"GiaDongCua":12.5,"ThayDoi":"0.3(2.46 %)","KhoiLuongKhopLenh":900,"GiaTriKhopLenh":11160000,"KLThoaThuan":0,"GtThoaThuan":0,"GiaMoCua":12.3,"GiaCaoNhat":12.5,"GiaThapNhat":12.3},{"Ngay":"21/09/2023","GiaDieuChinh":11.67,"GiaDongCua":12.2,"ThayDoi":"0.2(1.67 %)","KhoiLuongKhopLenh":329,"GiaTriKhopLenh":3988000,"KLThoaThuan":0,"GtThoaThuan":0,"GiaMoCua":12,"GiaCaoNhat":12.2,"GiaThapNhat":12},{"Ngay":"20/09/2023","GiaDieuChinh":11.48,"GiaDongCua":12,"ThayDoi":"0(0.00 %)","KhoiLuongKhopLenh":3702,"GiaTriKhopLenh":44514000,"KLThoaThuan":0,"GtThoaThuan":0,"GiaMoCua":12.2,"GiaCaoNhat":12.2,"GiaThapNhat":12},{"Ngay":"18/09/2023","GiaDieuChinh":11.48,"GiaDongCua":12,"ThayDoi":"-0.5(-4.00 %)","KhoiLuongKhopLenh":13302,"GiaTriKhopLenh":161895600,"KLThoaThuan":0,"GtThoaThuan":0,"GiaMoCua":12.5,"GiaCaoNhat":12.5,"GiaThapNhat":12},{"Ngay":"14/09/2023","GiaDieuChinh":11.96,"GiaDongCua":12.5,"ThayDoi":"0(0.00 %)","KhoiLuongKhopLenh":1000,"GiaTriKhopLenh":12500000,"KLThoaThuan":0,"GtThoaThuan":0,"GiaMoCua":12.5,"GiaCaoNhat":12.5,"GiaThapNhat":12.5},{"Ngay":"13/09/2023","GiaDieuChinh":11.96,"GiaDongCua":12.5,"ThayDoi":"0(0.00 %)","KhoiLuongKhopLenh":200,"GiaTriKhopLenh":2500000,"KLThoaThuan":0,"GtThoaThuan":0,"GiaMoCua":12.5,"GiaCaoNhat":12.5,"GiaThapNhat":12.5},{"Ngay":"12/09/2023","GiaDieuChinh":11.96,"GiaDongCua":12.5,"ThayDoi":"-0.5(-3.85 %)","KhoiLuongKhopLenh":10408,"GiaTriKhopLenh":132994500,"KLThoaThuan":0,"GtThoaThuan":0,"GiaMoCua":12.9,"GiaCaoNhat":12.9,"GiaThapNhat":12.5},{"Ngay":"11/09/2023","GiaDieuChinh":12.44,"GiaDongCua":13,"ThayDoi":"-0.3(-2.26 %)","KhoiLuongKhopLenh":700,"GiaTriKhopLenh":9130000,"KLThoaThuan":0,"GtThoaThuan":0,"GiaMoCua":13.3,"GiaCaoNhat":13.3,"GiaThapNhat":13},{"Ngay":"08/09/2023","GiaDieuChinh":12.72,"GiaDongCua":13.3,"ThayDoi":"-0.2(-1.48 %)","KhoiLuongKhopLenh":29700,"GiaTriKhopLenh":400750000,"KLThoaThuan":0,"GtThoaThuan":0,"GiaMoCua":13.5,"GiaCaoNhat":13.5,"GiaThapNhat":13.3},{"Ngay":"07/09/2023","GiaDieuChinh":12.91,"GiaDongCua":13.5,"ThayDoi":"-0.1(-0.74 %)","KhoiLuongKhopLenh":2220,"GiaTriKhopLenh":29980000,"KLThoaThuan":0,"GtThoaThuan":0,"GiaMoCua":13.6,"GiaCaoNhat":13.6,"GiaThapNhat":13.5},{"Ngay":"06/09/2023","GiaDieuChinh":13.01,"GiaDongCua":13.6,"ThayDoi":"0(0.00 %)","KhoiLuongKhopLenh":0,"GiaTriKhopLenh":0,"KLThoaThuan":0,"GtThoaThuan":0,"GiaMoCua":13.6,"GiaCaoNhat":13.6,"GiaThapNhat":13.6},{"Ngay":"05/09/2023","GiaDieuChinh":13.01,"GiaDongCua":13.6,"ThayDoi":"0(0.00 %)","KhoiLuongKhopLenh":601,"GiaTriKhopLenh":8173700,"KLThoaThuan":0,"GtThoaThuan":0,"GiaMoCua":13.6,"GiaCaoNhat":13.6,"GiaThapNhat":13.6},{"Ngay":"31/08/2023","GiaDieuChinh":13.01,"GiaDongCua":13.6,"ThayDoi":"0(0.00 %)","KhoiLuongKhopLenh":0,"GiaTriKhopLenh":0,"KLThoaThuan":0,"GtThoaThuan":0,"GiaMoCua":13.6,"GiaCaoNhat":13.6,"GiaThapNhat":13.6},{"Ngay":"30/08/2023","GiaDieuChinh":13.01,"GiaDongCua":13.6,"ThayDoi":"0.1(0.74 %)","KhoiLuongKhopLenh":110,"GiaTriKhopLenh":1496000,"KLThoaThuan":0,"GtThoaThuan":0,"GiaMoCua":13.6,"GiaCaoNhat":13.6,"GiaThapNhat":13.6},{"Ngay":"29/08/2023","GiaDieuChinh":12.91,"GiaDongCua":13.5,"ThayDoi":"0(0.00 %)","KhoiLuongKhopLenh":0,"GiaTriKhopLenh":0,"KLThoaThuan":0,"GtThoaThuan":0,"GiaMoCua":13.5,"GiaCaoNhat":13.5,"GiaThapNhat":13.5},{"Ngay":"28/08/2023","GiaDieuChinh":12.91,"GiaDongCua":13.5,"ThayDoi":"0(0.00 %)","KhoiLuongKhopLenh":5800,"GiaTriKhopLenh":78030000,"KLThoaThuan":0,"GtThoaThuan":0,"GiaMoCua":13.5,"GiaCaoNhat":13.5,"GiaThapNhat":13.2},{"Ngay":"25/08/2023","GiaDieuChinh":12.91,"GiaDongCua":13.5,"ThayDoi":"0(0.00 %)","KhoiLuongKhopLenh":40537,"GiaTriKhopLenh":547253200,"KLThoaThuan":0,"GtThoaThuan":0,"GiaMoCua":13.5,"GiaCaoNhat":13.5,"GiaThapNhat":13.5},{"Ngay":"24/08/2023","GiaDieuChinh":12.91,"GiaDongCua":13.5,"ThayDoi":"0.2(1.50 %)","KhoiLuongKhopLenh":110,"GiaTriKhopLenh":1483000,"KLThoaThuan":0,"GtThoaThuan":0,"GiaMoCua":13.5,"GiaCaoNhat":13.5,"GiaThapNhat":13.5},{"Ngay":"23/08/2023","GiaDieuChinh":12.72,"GiaDongCua":13.3,"ThayDoi":"-0.5(-3.62 %)","KhoiLuongKhopLenh":5400,"GiaTriKhopLenh":73880000,"KLThoaThuan":0,"GtThoaThuan":0,"GiaMoCua":13.7,"GiaCaoNhat":13.7,"GiaThapNhat":13.3},{"Ngay":"22/08/2023","GiaDieuChinh":13.2,"GiaDongCua":13.8,"ThayDoi":"0(0.00 %)","KhoiLuongKhopLenh":10047,"GiaTriKhopLenh":138615000,"KLThoaThuan":0,"GtThoaThuan":0,"GiaMoCua":13.8,"GiaCaoNhat":13.8,"GiaThapNhat":13.8},{"Ngay":"21/08/2023","GiaDieuChinh":13.2,"GiaDongCua":13.8,"ThayDoi":"-0.6(-4.17 %)","KhoiLuongKhopLenh":8000,"GiaTriKhopLenh":109460000,"KLThoaThuan":0,"GtThoaThuan":0,"GiaMoCua":13.2,"GiaCaoNhat":14,"GiaThapNhat":13.1},{"Ngay":"18/08/2023","GiaDieuChinh":13.78,"GiaDongCua":14.4,"ThayDoi":"-1.5(-9.43 %)","KhoiLuongKhopLenh":1100,"GiaTriKhopLenh":15840000,"KLThoaThuan":0,"GtThoaThuan":0,"GiaMoCua":14.4,"GiaCaoNhat":14.4,"GiaThapNhat":14.4},{"Ngay":"17/08/2023","GiaDieuChinh":15.21,"GiaDongCua":15.9,"ThayDoi":"1.3(8.90 %)","KhoiLuongKhopLenh":100,"GiaTriKhopLenh":1590000,"KLThoaThuan":0,"GtThoaThuan":0,"GiaMoCua":15.9,"GiaCaoNhat":15.9,"GiaThapNhat":15.9},{"Ngay":"16/08/2023","GiaDieuChinh":13.97,"GiaDongCua":14.6,"ThayDoi":"-0.9(-5.81 %)","KhoiLuongKhopLenh":4864,"GiaTriKhopLenh":68693500,"KLThoaThuan":0,"GtThoaThuan":0,"GiaMoCua":14.2,"GiaCaoNhat":15.3,"GiaThapNhat":14},{"Ngay":"15/08/2023","GiaDieuChinh":14.83,"GiaDongCua":15.5,"ThayDoi":"1.3(9.15 %)","KhoiLuongKhopLenh":8000,"GiaTriKhopLenh":110550000,"KLThoaThuan":0,"GtThoaThuan":0,"GiaMoCua":14.2,"GiaCaoNhat":15.6,"GiaThapNhat":13.6},{"Ngay":"14/08/2023","GiaDieuChinh":13.58,"GiaDongCua":14.2,"ThayDoi":"-0.1(-0.70 %)","KhoiLuongKhopLenh":2000,"GiaTriKhopLenh":28400000,"KLThoaThuan":0,"GtThoaThuan":0,"GiaMoCua":14.2,"GiaCaoNhat":14.2,"GiaThapNhat":14.2},{"Ngay":"11/08/2023","GiaDieuChinh":13.68,"GiaDongCua":14.3,"ThayDoi":"0.3(2.14 %)","KhoiLuongKhopLenh":2200,"GiaTriKhopLenh":30850000,"KLThoaThuan":0,"GtThoaThuan":0,"GiaMoCua":14,"GiaCaoNhat":14.3,"GiaThapNhat":14},{"Ngay":"10/08/2023","GiaDieuChinh":13.39,"GiaDongCua":14,"ThayDoi":"-0.5(-3.45 %)","KhoiLuongKhopLenh":1000,"GiaTriKhopLenh":14110000,"KLThoaThuan":0,"GtThoaThuan":0,"GiaMoCua":14.2,"GiaCaoNhat":14.3,"GiaThapNhat":14},{"Ngay":"09/08/2023","GiaDieuChinh":13.87,"GiaDongCua":14.5,"ThayDoi":"0.4(2.84 %)","KhoiLuongKhopLenh":620,"GiaTriKhopLenh":8835000,"KLThoaThuan":0,"GtThoaThuan":0,"GiaMoCua":14.1,"GiaCaoNhat":14.5,"GiaThapNhat":14.1},{"Ngay":"08/08/2023","GiaDieuChinh":13.49,"GiaDongCua":14.1,"ThayDoi":"-0.1(-0.70 %)","KhoiLuongKhopLenh":5600,"GiaTriKhopLenh":76920000,"KLThoaThuan":0,"GtThoaThuan":0,"GiaMoCua":13.7,"GiaCaoNhat":14.5,"GiaThapNhat":13.5},{"Ngay":"07/08/2023","GiaDieuChinh":13.58,"GiaDongCua":14.2,"ThayDoi":"-0.6(-4.05 %)","KhoiLuongKhopLenh":370,"GiaTriKhopLenh":5208000,"KLThoaThuan":0,"GtThoaThuan":0,"GiaMoCua":14,"GiaCaoNhat":14.5,"GiaThapNhat":14},{"Ngay":"04/08/2023","GiaDieuChinh":14.16,"GiaDongCua":14.8,"ThayDoi":"0(0.00 %)","KhoiLuongKhopLenh":1,"GiaTriKhopLenh":14800,"KLThoaThuan":0,"GtThoaThuan":0,"GiaMoCua":14.8,"GiaCaoNhat":14.8,"GiaThapNhat":14.8},{"Ngay":"03/08/2023","GiaDieuChinh":14.16,"GiaDongCua":14.8,"ThayDoi":"0(0.00 %)","KhoiLuongKhopLenh":0,"GiaTriKhopLenh":0,"KLThoaThuan":0,"GtThoaThuan":0,"GiaMoCua":14.8,"GiaCaoNhat":14.8,"GiaThapNhat":14.8},{"Ngay":"02/08/2023","GiaDieuChinh":14.16,"GiaDongCua":14.8,"ThayDoi":"-0.3(-1.99 %)","KhoiLuongKhopLenh":1800,"GiaTriKhopLenh":24980000,"KLThoaThuan":0,"GtThoaThuan":0,"GiaMoCua":14,"GiaCaoNhat":14.8,"GiaThapNhat":13.7},{"Ngay":"01/08/2023","GiaDieuChinh":14.44,"GiaDongCua":15.1,"ThayDoi":"-0.9(-5.62 %)","KhoiLuongKhopLenh":500,"GiaTriKhopLenh":7520000,"KLThoaThuan":0,"GtThoaThuan":0,"GiaMoCua":16,"GiaCaoNhat":16,"GiaThapNhat":14.7},{"Ngay":"31/07/2023","GiaDieuChinh":15.31,"GiaDongCua":16,"ThayDoi":"0(0.00 %)","KhoiLuongKhopLenh":0,"GiaTriKhopLenh":0,"KLThoaThuan":0,"GtThoaThuan":0,"GiaMoCua":16,"GiaCaoNhat":16,"GiaThapNhat":16},{"Ngay":"28/07/2023","GiaDieuChinh":15.31,"GiaDongCua":16,"ThayDoi":"1.3(8.84 %)","KhoiLuongKhopLenh":100,"GiaTriKhopLenh":1600000,"KLThoaThuan":0,"GtThoaThuan":0,"GiaMoCua":16,"GiaCaoNhat":16,"GiaThapNhat":16},{"Ngay":"27/07/2023","GiaDieuChinh":14.06,"GiaDongCua":14.7,"ThayDoi":"-0.8(-5.16 %)","KhoiLuongKhopLenh":6700,"GiaTriKhopLenh":96700000,"KLThoaThuan":0,"GtThoaThuan":0,"GiaMoCua":15.5,"GiaCaoNhat":15.5,"GiaThapNhat":14},{"Ngay":"26/07/2023","GiaDieuChinh":14.83,"GiaDongCua":15.5,"ThayDoi":"0(0.00 %)","KhoiLuongKhopLenh":341,"GiaTriKhopLenh":5354000,"KLThoaThuan":0,"GtThoaThuan":0,"GiaMoCua":16.8,"GiaCaoNhat":16.8,"GiaThapNhat":15.5},{"Ngay":"25/07/2023","GiaDieuChinh":14.83,"GiaDongCua":15.5,"ThayDoi":"1.3(9.15 %)","KhoiLuongKhopLenh":100,"GiaTriKhopLenh":1550000,"KLThoaThuan":0,"GtThoaThuan":0,"GiaMoCua":15.5,"GiaCaoNhat":15.5,"GiaThapNhat":15.5},{"Ngay":"24/07/2023","GiaDieuChinh":13.58,"GiaDongCua":14.2,"ThayDoi":"-0.3(-2.07 %)","KhoiLuongKhopLenh":1500,"GiaTriKhopLenh":21460000,"KLThoaThuan":0,"GtThoaThuan":0,"GiaMoCua":14,"GiaCaoNhat":14.5,"GiaThapNhat":14},{"Ngay":"21/07/2023","GiaDieuChinh":13.87,"GiaDongCua":14.5,"ThayDoi":"0.5(3.57 %)","KhoiLuongKhopLenh":6420,"GiaTriKhopLenh":90130000,"KLThoaThuan":0,"GtThoaThuan":0,"GiaMoCua":14,"GiaCaoNhat":14.5,"GiaThapNhat":14},{"Ngay":"20/07/2023","GiaDieuChinh":13.39,"GiaDongCua":14,"ThayDoi":"-0.3(-2.10 %)","KhoiLuongKhopLenh":1300,"GiaTriKhopLenh":18040000,"KLThoaThuan":0,"GtThoaThuan":0,"GiaMoCua":13.6,"GiaCaoNhat":14,"GiaThapNhat":13.6},{"Ngay":"19/07/2023","GiaDieuChinh":13.68,"GiaDongCua":14.3,"ThayDoi":"0.1(0.70 %)","KhoiLuongKhopLenh":2502,"GiaTriKhopLenh":35898800,"KLThoaThuan":0,"GtThoaThuan":0,"GiaMoCua":14.4,"GiaCaoNhat":14.4,"GiaThapNhat":14},{"Ngay":"18/07/2023","GiaDieuChinh":13.58,"GiaDongCua":14.2,"ThayDoi":"-0.3(-2.07 %)","KhoiLuongKhopLenh":500,"GiaTriKhopLenh":7160000,"KLThoaThuan":0,"GtThoaThuan":0,"GiaMoCua":14.4,"GiaCaoNhat":14.4,"GiaThapNhat":14.2},{"Ngay":"17/07/2023","GiaDieuChinh":13.87,"GiaDongCua":14.5,"ThayDoi":"0.3(2.11 %)","KhoiLuongKhopLenh":2000,"GiaTriKhopLenh":28200000,"KLThoaThuan":0,"GtThoaThuan":0,"GiaMoCua":14,"GiaCaoNhat":14.5,"GiaThapNhat":14},{"Ngay":"14/07/2023","GiaDieuChinh":13.58,"GiaDongCua":14.2,"ThayDoi":"0(0.00 %)","KhoiLuongKhopLenh":0,"GiaTriKhopLenh":0,"KLThoaThuan":0,"GtThoaThuan":0,"GiaMoCua":14.2,"GiaCaoNhat":14.2,"GiaThapNhat":14.2},{"Ngay":"13/07/2023","GiaDieuChinh":13.58,"GiaDongCua":14.2,"ThayDoi":"0(0.00 %)","KhoiLuongKhopLenh":2400,"GiaTriKhopLenh":33910000,"KLThoaThuan":0,"GtThoaThuan":0,"GiaMoCua":14.1,"GiaCaoNhat":14.5,"GiaThapNhat":14},{"Ngay":"12/07/2023","GiaDieuChinh":13.58,"GiaDongCua":14.2,"ThayDoi":"0(0.00 %)","KhoiLuongKhopLenh":1401,"GiaTriKhopLenh":19633500,"KLThoaThuan":0,"GtThoaThuan":0,"GiaMoCua":14,"GiaCaoNhat":14.2,"GiaThapNhat":13.9},{"Ngay":"11/07/2023","GiaDieuChinh":13.58,"GiaDongCua":14.2,"ThayDoi":"-0.2(-1.39 %)","KhoiLuongKhopLenh":300,"GiaTriKhopLenh":4240000,"KLThoaThuan":0,"GtThoaThuan":0,"GiaMoCua":14,"GiaCaoNhat":14.2,"GiaThapNhat":14},{"Ngay":"07/07/2023","GiaDieuChinh":13.78,"GiaDongCua":14.4,"ThayDoi":"0.1(0.70 %)","KhoiLuongKhopLenh":600,"GiaTriKhopLenh":8040000,"KLThoaThuan":0,"GtThoaThuan":0,"GiaMoCua":13,"GiaCaoNhat":14.4,"GiaThapNhat":13},{"Ngay":"06/07/2023","GiaDieuChinh":13.68,"GiaDongCua":14.3,"ThayDoi":"-0.2(-1.38 %)","KhoiLuongKhopLenh":1700,"GiaTriKhopLenh":23890000,"KLThoaThuan":0,"GtThoaThuan":0,"GiaMoCua":14,"GiaCaoNhat":14.3,"GiaThapNhat":14},{"Ngay":"05/07/2023","GiaDieuChinh":13.87,"GiaDongCua":14.5,"ThayDoi":"-0.3(-2.03 %)","KhoiLuongKhopLenh":2200,"GiaTriKhopLenh":30850000,"KLThoaThuan":0,"GtThoaThuan":0,"GiaMoCua":14,"GiaCaoNhat":14.5,"GiaThapNhat":14},{"Ngay":"04/07/2023","GiaDieuChinh":14.16,"GiaDongCua":14.8,"ThayDoi":"0.2(1.37 %)","KhoiLuongKhopLenh":100,"GiaTriKhopLenh":1480000,"KLThoaThuan":0,"GtThoaThuan":0,"GiaMoCua":14.8,"GiaCaoNhat":14.8,"GiaThapNhat":14.8},{"Ngay":"03/07/2023","GiaDieuChinh":13.97,"GiaDongCua":14.6,"ThayDoi":"-0.1(-0.68 %)","KhoiLuongKhopLenh":11800,"GiaTriKhopLenh":172280000,"KLThoaThuan":0,"GtThoaThuan":0,"GiaMoCua":14.6,"GiaCaoNhat":14.6,"GiaThapNhat":14.6},{"Ngay":"29/06/2023","GiaDieuChinh":14.16,"GiaDongCua":14.8,"ThayDoi":"-0.1(-0.67 %)","KhoiLuongKhopLenh":15800,"GiaTriKhopLenh":233840000,"KLThoaThuan":0,"GtThoaThuan":0,"GiaMoCua":14.8,"GiaCaoNhat":14.8,"GiaThapNhat":14.8},{"Ngay":"28/06/2023","GiaDieuChinh":14.25,"GiaDongCua":14.9,"ThayDoi":"0(0.00 %)","KhoiLuongKhopLenh":300,"GiaTriKhopLenh":4420000,"KLThoaThuan":0,"GtThoaThuan":0,"GiaMoCua":14.7,"GiaCaoNhat":14.9,"GiaThapNhat":14.6},{"Ngay":"27/06/2023","GiaDieuChinh":14.25,"GiaDongCua":14.9,"ThayDoi":"0(0.00 %)","KhoiLuongKhopLenh":900,"GiaTriKhopLenh":13910000,"KLThoaThuan":0,"GtThoaThuan":0,"GiaMoCua":15,"GiaCaoNhat":15.8,"GiaThapNhat":14.9},{"Ngay":"26/06/2023","GiaDieuChinh":14.25,"GiaDongCua":14.9,"ThayDoi":"0(0.00 %)","KhoiLuongKhopLenh":1,"GiaTriKhopLenh":14300,"KLThoaThuan":0,"GtThoaThuan":0,"GiaMoCua":14.9,"GiaCaoNhat":14.9,"GiaThapNhat":14.9},{"Ngay":"23/06/2023","GiaDieuChinh":14.25,"GiaDongCua":14.9,"ThayDoi":"0(0.00 %)","KhoiLuongKhopLenh":55,"GiaTriKhopLenh":808500,"KLThoaThuan":0,"GtThoaThuan":0,"GiaMoCua":14.9,"GiaCaoNhat":14.9,"GiaThapNhat":14.9},{"Ngay":"22/06/2023","GiaDieuChinh":14.25,"GiaDongCua":14.9,"ThayDoi":"0.2(1.36 %)","KhoiLuongKhopLenh":6000,"GiaTriKhopLenh":87950000,"KLThoaThuan":0,"GtThoaThuan":0,"GiaMoCua":14.6,"GiaCaoNhat":14.9,"GiaThapNhat":14.6},{"Ngay":"21/06/2023","GiaDieuChinh":14.06,"GiaDongCua":14.7,"ThayDoi":"0(0.00 %)","KhoiLuongKhopLenh":1600,"GiaTriKhopLenh":23020000,"KLThoaThuan":0,"GtThoaThuan":0,"GiaMoCua":14.7,"GiaCaoNhat":14.7,"GiaThapNhat":14.2},{"Ngay":"19/06/2023","GiaDieuChinh":14.06,"GiaDongCua":14.7,"ThayDoi":"0(0.00 %)","KhoiLuongKhopLenh":0,"GiaTriKhopLenh":0,"KLThoaThuan":0,"GtThoaThuan":0,"GiaMoCua":14.7,"GiaCaoNhat":14.7,"GiaThapNhat":14.7},{"Ngay":"16/06/2023","GiaDieuChinh":14.06,"GiaDongCua":14.7,"ThayDoi":"0.4(2.80 %)","KhoiLuongKhopLenh":3434,"GiaTriKhopLenh":49126000,"KLThoaThuan":0,"GtThoaThuan":0,"GiaMoCua":14.2,"GiaCaoNhat":14.7,"GiaThapNhat":14.2},{"Ngay":"15/06/2023","GiaDieuChinh":13.68,"GiaDongCua":14.3,"ThayDoi":"-0.3(-2.05 %)","KhoiLuongKhopLenh":11503,"GiaTriKhopLenh":164493800,"KLThoaThuan":0,"GtThoaThuan":0,"GiaMoCua":14.3,"GiaCaoNhat":14.3,"GiaThapNhat":14.3},{"Ngay":"14/06/2023","GiaDieuChinh":13.97,"GiaDongCua":14.6,"ThayDoi":"0(0.00 %)","KhoiLuongKhopLenh":1200,"GiaTriKhopLenh":17360000,"KLThoaThuan":0,"GtThoaThuan":0,"GiaMoCua":14.5,"GiaCaoNhat":14.6,"GiaThapNhat":14},{"Ngay":"13/06/2023","GiaDieuChinh":14.6,"GiaDongCua":14.6,"ThayDoi":"0(0.00 %)","KhoiLuongKhopLenh":140,"GiaTriKhopLenh":1862400,"KLThoaThuan":0,"GtThoaThuan":0,"GiaMoCua":14.6,"GiaCaoNhat":14.6,"GiaThapNhat":14.6},{"Ngay":"12/06/2023","GiaDieuChinh":13.97,"GiaDongCua":14.6,"ThayDoi":"-1.3(-8.18 %)","KhoiLuongKhopLenh":1737,"GiaTriKhopLenh":25360200,"KLThoaThuan":0,"GtThoaThuan":0,"GiaMoCua":14.6,"GiaCaoNhat":14.6,"GiaThapNhat":14.6},{"Ngay":"09/06/2023","GiaDieuChinh":15.21,"GiaDongCua":15.9,"ThayDoi":"1.1(7.43 %)","KhoiLuongKhopLenh":200,"GiaTriKhopLenh":3070000,"KLThoaThuan":0,"GtThoaThuan":0,"GiaMoCua":14.8,"GiaCaoNhat":15.9,"GiaThapNhat":14.8},{"Ngay":"08/06/2023","GiaDieuChinh":14.16,"GiaDongCua":14.8,"ThayDoi":"0.3(2.07 %)","KhoiLuongKhopLenh":10200,"GiaTriKhopLenh":147930000,"KLThoaThuan":0,"GtThoaThuan":0,"GiaMoCua":14.5,"GiaCaoNhat":14.8,"GiaThapNhat":14.5},{"Ngay":"07/06/2023","GiaDieuChinh":13.87,"GiaDongCua":14.5,"ThayDoi":"-0.7(-4.61 %)","KhoiLuongKhopLenh":1000,"GiaTriKhopLenh":14300000,"KLThoaThuan":0,"GtThoaThuan":0,"GiaMoCua":15,"GiaCaoNhat":15,"GiaThapNhat":14},{"Ngay":"06/06/2023","GiaDieuChinh":14.54,"GiaDongCua":15.2,"ThayDoi":"0(0.00 %)","KhoiLuongKhopLenh":0,"GiaTriKhopLenh":0,"KLThoaThuan":0,"GtThoaThuan":0,"GiaMoCua":15.2,"GiaCaoNhat":15.2,"GiaThapNhat":15.2},{"Ngay":"05/06/2023","GiaDieuChinh":14.54,"GiaDongCua":15.2,"ThayDoi":"0(0.00 %)","KhoiLuongKhopLenh":0,"GiaTriKhopLenh":0,"KLThoaThuan":0,"GtThoaThuan":0,"GiaMoCua":15.2,"GiaCaoNhat":15.2,"GiaThapNhat":15.2},{"Ngay":"02/06/2023","GiaDieuChinh":14.54,"GiaDongCua":15.2,"ThayDoi":"0(0.00 %)","KhoiLuongKhopLenh":20,"GiaTriKhopLenh":305500,"KLThoaThuan":0,"GtThoaThuan":0,"GiaMoCua":15.2,"GiaCaoNhat":15.2,"GiaThapNhat":15.2},{"Ngay":"01/06/2023","GiaDieuChinh":14.54,"GiaDongCua":15.2,"ThayDoi":"0(0.00 %)","KhoiLuongKhopLenh":2855,"GiaTriKhopLenh":42082500,"KLThoaThuan":0,"GtThoaThuan":0,"GiaMoCua":15.9,"GiaCaoNhat":15.9,"GiaThapNhat":14.5},{"Ngay":"31/05/2023","GiaDieuChinh":14.54,"GiaDongCua":15.2,"ThayDoi":"-0.3(-1.94 %)","KhoiLuongKhopLenh":8100,"GiaTriKhopLenh":120670000,"KLThoaThuan":0,"GtThoaThuan":0,"GiaMoCua":16,"GiaCaoNhat":16,"GiaThapNhat":14.5},{"Ngay":"30/05/2023","GiaDieuChinh":14.83,"GiaDongCua":15.5,"ThayDoi":"1(6.90 %)","KhoiLuongKhopLenh":20200,"GiaTriKhopLenh":300660000,"KLThoaThuan":0,"GtThoaThuan":0,"GiaMoCua":14.5,"GiaCaoNhat":15.5,"GiaThapNhat":14.5},{"Ngay":"29/05/2023","GiaDieuChinh":13.87,"GiaDongCua":14.5,"ThayDoi":"0.5(3.57 %)","KhoiLuongKhopLenh":345,"GiaTriKhopLenh":4977500,"KLThoaThuan":0,"GtThoaThuan":0,"GiaMoCua":15.2,"GiaCaoNhat":15.2,"GiaThapNhat":14},{"Ngay":"26/05/2023","GiaDieuChinh":13.39,"GiaDongCua":14,"ThayDoi":"0(0.00 %)","KhoiLuongKhopLenh":2300,"GiaTriKhopLenh":32200000,"KLThoaThuan":0,"GtThoaThuan":0,"GiaMoCua":14,"GiaCaoNhat":14,"GiaThapNhat":14},{"Ngay":"25/05/2023","GiaDieuChinh":13.39,"GiaDongCua":14,"ThayDoi":"-0.5(-3.45 %)","KhoiLuongKhopLenh":2300,"GiaTriKhopLenh":32200000,"KLThoaThuan":0,"GtThoaThuan":0,"GiaMoCua":14,"GiaCaoNhat":14,"GiaThapNhat":14},{"Ngay":"24/05/2023","GiaDieuChinh":13.87,"GiaDongCua":14.5,"ThayDoi":"-0.1(-0.68 %)","KhoiLuongKhopLenh":12100,"GiaTriKhopLenh":165830000,"KLThoaThuan":0,"GtThoaThuan":0,"GiaMoCua":14.5,"GiaCaoNhat":14.5,"GiaThapNhat":13.4},{"Ngay":"23/05/2023","GiaDieuChinh":13.97,"GiaDongCua":14.6,"ThayDoi":"0(0.00 %)","KhoiLuongKhopLenh":1200,"GiaTriKhopLenh":17520000,"KLThoaThuan":0,"GtThoaThuan":0,"GiaMoCua":14.6,"GiaCaoNhat":14.6,"GiaThapNhat":14.6},{"Ngay":"22/05/2023","GiaDieuChinh":13.97,"GiaDongCua":14.6,"ThayDoi":"-0.4(-2.67 %)","KhoiLuongKhopLenh":2001,"GiaTriKhopLenh":29435000,"KLThoaThuan":0,"GtThoaThuan":0,"GiaMoCua":15,"GiaCaoNhat":15,"GiaThapNhat":14.6},{"Ngay":"19/05/2023","GiaDieuChinh":14.35,"GiaDongCua":15,"ThayDoi":"-0.2(-1.32 %)","KhoiLuongKhopLenh":30000,"GiaTriKhopLenh":450000000,"KLThoaThuan":0,"GtThoaThuan":0,"GiaMoCua":15,"GiaCaoNhat":15,"GiaThapNhat":15},{"Ngay":"18/05/2023","GiaDieuChinh":14.54,"GiaDongCua":15.2,"ThayDoi":"0(0.00 %)","KhoiLuongKhopLenh":0,"GiaTriKhopLenh":0,"KLThoaThuan":0,"GtThoaThuan":0,"GiaMoCua":15.2,"GiaCaoNhat":15.2,"GiaThapNhat":15.2},{"Ngay":"17/05/2023","GiaDieuChinh":14.54,"GiaDongCua":15.2,"ThayDoi":"0(0.00 %)","KhoiLuongKhopLenh":36,"GiaTriKhopLenh":547200,"KLThoaThuan":0,"GtThoaThuan":0,"GiaMoCua":15.2,"GiaCaoNhat":15.2,"GiaThapNhat":15.2},{"Ngay":"16/05/2023","GiaDieuChinh":14.54,"GiaDongCua":15.2,"ThayDoi":"0(0.00 %)","KhoiLuongKhopLenh":0,"GiaTriKhopLenh":0,"KLThoaThuan":0,"GtThoaThuan":0,"GiaMoCua":15.2,"GiaCaoNhat":15.2,"GiaThapNhat":15.2},{"Ngay":"15/05/2023","GiaDieuChinh":15.2,"GiaDongCua":15.2,"ThayDoi":"0.5(3.40 %)","KhoiLuongKhopLenh":100,"GiaTriKhopLenh":1520000,"KLThoaThuan":0,"GtThoaThuan":0,"GiaMoCua":15.2,"GiaCaoNhat":15.2,"GiaThapNhat":15.2},{"Ngay":"12/05/2023","GiaDieuChinh":14.06,"GiaDongCua":14.7,"ThayDoi":"0.7(5.00 %)","KhoiLuongKhopLenh":100,"GiaTriKhopLenh":1470000,"KLThoaThuan":0,"GtThoaThuan":0,"GiaMoCua":14.7,"GiaCaoNhat":14.7,"GiaThapNhat":14.7},{"Ngay":"11/05/2023","GiaDieuChinh":13.39,"GiaDongCua":14,"ThayDoi":"-1.3(-8.50 %)","KhoiLuongKhopLenh":300,"GiaTriKhopLenh":4280000,"KLThoaThuan":0,"GtThoaThuan":0,"GiaMoCua":14.8,"GiaCaoNhat":14.8,"GiaThapNhat":14},{"Ngay":"10/05/2023","GiaDieuChinh":14.64,"GiaDongCua":15.3,"ThayDoi":"0(0.00 %)","KhoiLuongKhopLenh":0,"GiaTriKhopLenh":0,"KLThoaThuan":0,"GtThoaThuan":0,"GiaMoCua":15.3,"GiaCaoNhat":15.3,"GiaThapNhat":15.3},{"Ngay":"09/05/2023","GiaDieuChinh":14.64,"GiaDongCua":15.3,"ThayDoi":"0(0.00 %)","KhoiLuongKhopLenh":100,"GiaTriKhopLenh":1530000,"KLThoaThuan":0,"GtThoaThuan":0,"GiaMoCua":15.3,"GiaCaoNhat":15.3,"GiaThapNhat":15.3},{"Ngay":"08/05/2023","GiaDieuChinh":14.64,"GiaDongCua":15.3,"ThayDoi":"0(0.00 %)","KhoiLuongKhopLenh":0,"GiaTriKhopLenh":0,"KLThoaThuan":0,"GtThoaThuan":0,"GiaMoCua":15.3,"GiaCaoNhat":15.3,"GiaThapNhat":15.3},{"Ngay":"05/05/2023","GiaDieuChinh":14.64,"GiaDongCua":15.3,"ThayDoi":"0(0.00 %)","KhoiLuongKhopLenh":0,"GiaTriKhopLenh":0,"KLThoaThuan":0,"GtThoaThuan":0,"GiaMoCua":15.3,"GiaCaoNhat":15.3,"GiaThapNhat":15.3},{"Ngay":"04/05/2023","GiaDieuChinh":14.64,"GiaDongCua":15.3,"ThayDoi":"